elastic_opentelemetry-1.11.0.dist-info/licenses/LICENSE
elastic_opentelemetry-1.11.0.dist-info/licenses/NOTICE.txt
elasticotel/distro/__init__.py
elasticotel/distro/config.py
elasticotel/distro/environment_variables.py
elasticotel/distro/py.typed
elasticotel/distro/resource_detectors.py
elasticotel/distro/sanitization.py
elasticotel/distro/version.py
elasticotel/instrumentation/__init__.py
elasticotel/instrumentation/bootstrap.py
elasticotel/sdk/__init__.py
elasticotel/sdk/py.typed
elasticotel/sdk/resources/__init__.py
elasticotel/sdk/sampler/__init__.py
opentelemetry/_opamp/__init__.py
opentelemetry/_opamp/agent.py
opentelemetry/_opamp/client.py
opentelemetry/_opamp/exceptions.py
opentelemetry/_opamp/messages.py
opentelemetry/_opamp/version.py
opentelemetry/_opamp/proto/anyvalue_pb2.py
opentelemetry/_opamp/proto/anyvalue_pb2.pyi
opentelemetry/_opamp/proto/opamp_pb2.py
opentelemetry/_opamp/proto/opamp_pb2.pyi
opentelemetry/_opamp/transport/base.py
opentelemetry/_opamp/transport/exceptions.py
opentelemetry/_opamp/transport/requests.py
elastic_opentelemetry-1.11.0.dist-info/METADATA
elastic_opentelemetry-1.11.0.dist-info/WHEEL
elastic_opentelemetry-1.11.0.dist-info/entry_points.txt
elastic_opentelemetry-1.11.0.dist-info/top_level.txt
elastic_opentelemetry-1.11.0.dist-info/RECORD
