Metadata-Version: 2.4
Name: elastic-opentelemetry
Version: 1.11.0
Summary: Elastic Distribution of OpenTelemetry Python
Author-email: Riccardo Magliocchetti <riccardo.magliocchetti@elastic.co>
Maintainer-email: Riccardo Magliocchetti <riccardo.magliocchetti@elastic.co>
License-Expression: Apache-2.0
Project-URL: Homepage, https://github.com/elastic/elastic-otel-python
Project-URL: Bug Tracker, https://github.com/elastic/elastic-otel-python/issues
Classifier: Development Status :: 3 - Alpha
Classifier: Intended Audience :: Developers
Classifier: Framework :: OpenTelemetry
Classifier: Framework :: OpenTelemetry :: Distros
Classifier: Programming Language :: Python
Classifier: Programming Language :: Python :: 3
Classifier: Programming Language :: Python :: 3.9
Classifier: Programming Language :: Python :: 3.10
Classifier: Programming Language :: Python :: 3.11
Classifier: Programming Language :: Python :: 3.12
Classifier: Programming Language :: Python :: 3.13
Classifier: Typing :: Typed
Requires-Python: >=3.9
License-File: LICENSE
License-File: NOTICE.txt
Requires-Dist: opentelemetry-api==1.39.1
Requires-Dist: opentelemetry-exporter-otlp==1.39.1
Requires-Dist: opentelemetry-instrumentation==0.60b1
Requires-Dist: opentelemetry-instrumentation-system-metrics==0.60b1
Requires-Dist: opentelemetry-resourcedetector-gcp~=1.8.0a0
Requires-Dist: opentelemetry-resource-detector-azure~=0.1.5
Requires-Dist: opentelemetry-resource-detector-containerid==0.60b1
Requires-Dist: opentelemetry-sdk==1.39.1
Requires-Dist: opentelemetry-sdk-extension-aws~=2.1.0
Requires-Dist: opentelemetry-semantic-conventions==0.60b1
Requires-Dist: packaging
Requires-Dist: uuid-utils
Provides-Extra: dev
Requires-Dist: pytest; extra == "dev"
Requires-Dist: pip-tools; extra == "dev"
Requires-Dist: oteltest==0.24.0; extra == "dev"
Requires-Dist: leb128; extra == "dev"
Requires-Dist: pytest-vcr; python_version > "3.9" and extra == "dev"
Dynamic: license-file
